cython_packages/main.c
cython_packages/main.cpython-39-x86_64-linux-gnu.so
cython_packages/main.pyx
cython_packages-0.1.4.dist-info/LICENSE
cython_packages-0.1.4.dist-info/WHEEL
cython_packages-0.1.4.dist-info/METADATA
cython_packages-0.1.4.dist-info/RECORD
