Metadata-Version: 2.1
Name: cython-packages
Version: 0.1.4
Summary: Example project for demonstrating proprietary PyPI packages
License: Proprietary
Author: Aotu
Requires-Python: >=3.6,<4.0
Classifier: License :: Other/Proprietary License
Classifier: Programming Language :: Python :: 3
Classifier: Programming Language :: Python :: 3.10
Classifier: Programming Language :: Python :: 3.6
Classifier: Programming Language :: Python :: 3.7
Classifier: Programming Language :: Python :: 3.8
Classifier: Programming Language :: Python :: 3.9
